geodev_mapping/__init__.py
geodev_mapping/common.py
geodev_mapping/geodev_mapping.py
geodev_mapping-0.0.2.dist-info/LICENSE
geodev_mapping-0.0.2.dist-info/METADATA
geodev_mapping-0.0.2.dist-info/WHEEL
geodev_mapping-0.0.2.dist-info/entry_points.txt
geodev_mapping-0.0.2.dist-info/top_level.txt
geodev_mapping-0.0.2.dist-info/RECORD
